semantiva-0.5.0.dist-info/METADATA
semantiva-0.5.0.dist-info/WHEEL
semantiva-0.5.0.dist-info/entry_points.txt
semantiva-0.5.0.dist-info/licenses/LICENSE
semantiva-0.5.0.dist-info/licenses/NOTICE
semantiva/__init__.py
semantiva/cli/__init__.py
semantiva/cli/__main__.py
semantiva/configurations/__init__.py
semantiva/configurations/load_pipeline_from_yaml.py
semantiva/configurations/schema.py
semantiva/context_processors/__init__.py
semantiva/context_processors/context_observer.py
semantiva/context_processors/context_processors.py
semantiva/context_processors/context_types.py
semantiva/context_processors/factory.py
semantiva/contracts/__init__.py
semantiva/contracts/expectations.py
semantiva/contracts/messages.py
semantiva/core/__init__.py
semantiva/core/semantiva_component.py
semantiva/core/semantiva_predicate_map.py
semantiva/data_io/__init__.py
semantiva/data_io/data_io.py
semantiva/data_processors/__init__.py
semantiva/data_processors/copy_data_probe.py
semantiva/data_processors/data_dump.py
semantiva/data_processors/data_processors.py
semantiva/data_processors/data_slicer_factory.py
semantiva/data_processors/io_operation_factory.py
semantiva/data_processors/parametric_sweep_factory.py
semantiva/data_types/__init__.py
semantiva/data_types/data_types.py
semantiva/doctor/__init__.py
semantiva/doctor/jupyter.py
semantiva/examples/__init__.py
semantiva/examples/export_ontology.py
semantiva/examples/extension.py
semantiva/examples/from_context_sweep_demo.yaml
semantiva/examples/job_demo.py
semantiva/examples/simple_pipeline.yaml
semantiva/examples/test_utils.py
semantiva/exceptions/__init__.py
semantiva/exceptions/pipeline_exceptions.py
semantiva/execution/__init__.py
semantiva/execution/component_registry.py
semantiva/execution/executor/__init__.py
semantiva/execution/executor/executor.py
semantiva/execution/job_queue/__init__.py
semantiva/execution/job_queue/logging_setup.py
semantiva/execution/job_queue/queue_orchestrator.py
semantiva/execution/job_queue/worker.py
semantiva/execution/orchestrator/__init__.py
semantiva/execution/orchestrator/factory.py
semantiva/execution/orchestrator/orchestrator.py
semantiva/execution/run_space.py
semantiva-0.5.0.dist-info/RECORD
