Metadata-Version: 2.4
Name: semantiva
Version: 0.5.0
Summary: Semantiva: An HPC-ready, domain-driven, type-oriented framework that delivers semantic transparency to advanced scientific computing.
License-Expression: Apache-2.0
Requires-Python: >=3.10.12
Requires-Dist: numpy>=1.21.2
Requires-Dist: pyyaml>=6.0
Requires-Dist: rdflib>=4.2.2
Requires-Dist: typing_extensions>=4.3.0
Requires-Dist: jsonschema>=4.0.0
Requires-Dist: referencing>=0.2.0
